finalsa/i18n/__init__.py
finalsa/i18n/common/__init__.py
finalsa/i18n/common/country.py
finalsa/i18n/common/currency.py
finalsa/i18n/common/gender.py
finalsa/i18n/common/language.py
finalsa/i18n/common/marital_status.py
finalsa/i18n/common/occupation.py
finalsa/i18n/common/scholarity.py
finalsa_i18n-0.0.2.dist-info/METADATA
finalsa_i18n-0.0.2.dist-info/WHEEL
finalsa_i18n-0.0.2.dist-info/licenses/LICENSE.md
finalsa_i18n-0.0.2.dist-info/RECORD
