Metadata-Version: 2.4
Name: finalsa-i18n
Version: 0.0.2
Summary: Internationalization enums library for common data types used in business applications
Project-URL: Homepage, https://github.com/finalsa/finalsa-i18n
Project-URL: Documentation, https://github.com/finalsa/finalsa-i18n#readme
Project-URL: Repository, https://github.com/finalsa/finalsa-i18n.git
Project-URL: Issues, https://github.com/finalsa/finalsa-i18n/issues
Project-URL: Changelog, https://github.com/finalsa/finalsa-i18n/blob/main/CHANGELOG.md
Author-email: Luis Jimenez <luis@finalsa.com>
License: MIT License
License-File: LICENSE.md
Keywords: country,currency,education,enums,finalsa,gender,i18n,internationalization,language,localization,marital-status,occupation
Classifier: Development Status :: 4 - Beta
Classifier: Intended Audience :: Developers
Classifier: License :: OSI Approved :: MIT License
Classifier: Operating System :: OS Independent
Classifier: Programming Language :: Python :: 3
Classifier: Programming Language :: Python :: 3.9
Classifier: Programming Language :: Python :: 3.10
Classifier: Programming Language :: Python :: 3.11
Classifier: Programming Language :: Python :: 3.12
Classifier: Topic :: Software Development :: Internationalization
Classifier: Topic :: Software Development :: Libraries :: Python Modules
Classifier: Topic :: Software Development :: Localization
Classifier: Typing :: Typed
Requires-Python: >=3.9
